sdtf/__init__.py
sdtf/forest.py
sdtf-0.1.1.dist-info/LICENSE
sdtf-0.1.1.dist-info/METADATA
sdtf-0.1.1.dist-info/WHEEL
sdtf-0.1.1.dist-info/top_level.txt
sdtf-0.1.1.dist-info/RECORD
