Metadata-Version: 2.1
Name: sdtf
Version: 0.1.1
Summary: Exploring streaming options for decision trees and random forests. Based on scikit-learn fork.
Home-page: https://github.com/neurodata/SDTF
Author: Haoyin Xu
Author-email: haoyinxu@gmail.com
License: MIT
Download-URL: https://codeload.github.com/neurodata/SDTF/tar.gz/v0.1.1
Keywords: Streaming Trees,Machine Learning,Decision Trees
Platform: UNKNOWN
Classifier: Development Status :: 3 - Alpha
Classifier: Intended Audience :: Science/Research
Classifier: Topic :: Scientific/Engineering :: Artificial Intelligence
Classifier: License :: OSI Approved :: MIT License
Classifier: Programming Language :: Python :: 3
Classifier: Programming Language :: Python :: 3.6
Classifier: Programming Language :: Python :: 3.7
Classifier: Programming Language :: Python :: 3.8
Classifier: Programming Language :: Python :: 3.9
License-File: LICENSE
Requires-Dist: numpy
Requires-Dist: scipy
Requires-Dist: scikit-learn
Requires-Dist: matplotlib
Requires-Dist: seaborn
